oeg_feature_class/__init__.py
oeg_feature_class-1.1.dist-info/LICENSE
oeg_feature_class-1.1.dist-info/METADATA
oeg_feature_class-1.1.dist-info/WHEEL
oeg_feature_class-1.1.dist-info/top_level.txt
oeg_feature_class-1.1.dist-info/RECORD
